{
  "kind": "collectionType",
  "collectionName": "providers",
  "info": {
    "singularName": "provider",
    "pluralName": "providers",
    "displayName": "Provider"
  },
  "options": {
    "draftAndPublish": false
  },
  "pluginOptions": {},
  "attributes": {
    "name": {
      "type": "string"
    },
    "bio": {
      "type": "blocks"
    },
    "avatar": {
      "type": "media",
      "multiple": false,
      "allowedTypes": [
        "images",
        "files",
        "videos",
        "audios"
      ]
    },
    "verified": {
      "type": "boolean"
    },
    "listings": {
      "type": "relation",
      "relation": "oneToMany",
      "target": "api::listing.listing",
      "mappedBy": "provider"
    }
  }
}
